{"cameraMode":{"drawMode":0,"name":"Shaded","section":"Shading Mode"},"sceneLighting":true,"audioPlay":false,"sceneViewState":{"m_AlwaysRefresh":false,"showFog":true,"showSkybox":true,"showFlares":true,"showImageEffects":true,"showParticleSystems":true,"showVisualEffectGraphs":true,"m_FxEnabled":true},"in2DMode":false,"pivot":{"x":-365.5307312011719,"y":-1139.9774169921875,"z":-716.5491333007813},"rotation":{"x":0.11172395199537277,"y":-0.8589814901351929,"z":0.4524633586406708,"w":0.2121323198080063},"size":698.0879516601563,"orthographic":false}